setup.py
python_radius.egg-info/PKG-INFO
python_radius.egg-info/SOURCES.txt
python_radius.egg-info/dependency_links.txt
python_radius.egg-info/top_level.txt
python_radius.egg-info/zip-safe
radius/__init__.py