Metadata-Version: 1.1
Name: python-radius
Version: 1.0
Summary: Pure python radius implementation which supports Message-Authenticator and Status-Server.
Home-page: http://www.engledew.com
Author: Simon Engledew
Author-email: simon@engledew.com
License: MIT
Keywords: radius,Message-Authenticator,Status-Server
Platform: UNKNOWN
Classifier: Development Status :: 1 - Planning
Classifier: Operating System :: OS Independent
Classifier: Programming Language :: Python
